<?xml version="1.0" encoding="utf-8"?>
<testspecification purpose="administration" publisher="SBAC_PT" publishdate="Dec 19 2014  5:12PM" version="1.0">
  <identifier uniqueid="(SBAC_PT)SBAC Math HS-MATH-10-Spring-2014-2015" name="SBAC Math HS-MATH-10" label="Math HS Training Test " version="4867" />
  <property name="subject" value="MATH" label="MATH" />
  <property name="grade" value="10" label="grade 10" />
  <property name="grade" value="11" label="grade 11" />
  <property name="grade" value="12" label="grade 12" />
  <property name="grade" value="9" label="grade 9" />
  <property name="type" value="interim" label="interim" />
  <administration>
    <testblueprint>
      <bpelement elementtype="test" minopitems="0" maxopitems="8" minftitems="0" maxftitems="0" opitemcount="0" ftitemcount="11">
        <identifier uniqueid="(SBAC_PT)SBAC Math HS-MATH-10-Spring-2014-2015" name="SBAC Math HS-MATH-10" version="4867" />
      </bpelement>
      <bpelement elementtype="segment" minopitems="0" maxopitems="8" minftitems="0" maxftitems="0" opitemcount="0" ftitemcount="11">
        <identifier uniqueid="(SBAC_PT)SBAC Math HS-MATH-10-Spring-2014-2015" name="SBAC Math HS-MATH-10" version="4867" />
      </bpelement>
      <bpelement elementtype="strand" minopitems="0" maxopitems="8" opitemcount="0" ftitemcount="11">
        <identifier uniqueid="SBAC_PT-MA-Undesignated" name="MA-Undesignated" version="4867" />
      </bpelement>
    </testblueprint>
    <poolproperty property="--ITEMTYPE--" value="EQ" label="EQ" itemcount="2" />
    <poolproperty property="--ITEMTYPE--" value="ER" label="ER" itemcount="1" />
    <poolproperty property="--ITEMTYPE--" value="GI" label="GI" itemcount="3" />
    <poolproperty property="--ITEMTYPE--" value="MC" label="MC" itemcount="2" />
    <poolproperty property="--ITEMTYPE--" value="MI" label="MI" itemcount="1" />
    <poolproperty property="--ITEMTYPE--" value="MS" label="MS" itemcount="1" />
    <poolproperty property="--ITEMTYPE--" value="TI" label="TI" itemcount="1" />
    <poolproperty property="Language" value="ENU" label="English" itemcount="8" />
    <poolproperty property="Language" value="ENU-Braille" label="Braille English" itemcount="8" />
    <poolproperty property="Language" value="ESN" label="Spanish" itemcount="8" />
    <itempool>
      <testitem filename="item-187-1059.xml" itemtype="MS">
        <identifier uniqueid="187-1059" version="4867" />
        <bpref>(SBAC_PT)SBAC Math HS-MATH-10-Spring-2014-2015</bpref>
        <bpref>SBAC_PT-MA-Undesignated</bpref>
        <poolproperty property="--ITEMTYPE--" value="MS" label="MS" />
        <poolproperty property="Language" value="ENU" label="English" />
        <poolproperty property="Language" value="ENU-Braille" label="Braille English" />
        <poolproperty property="Language" value="ESN" label="Spanish" />
        <itemscoredimension measurementmodel="RAWSCORE" scorepoints="1" weight="1.000000000000000e+000" />
      </testitem>
      <testitem filename="item-187-1387.xml" itemtype="EQ">
        <identifier uniqueid="187-1387" version="4867" />
        <bpref>(SBAC_PT)SBAC Math HS-MATH-10-Spring-2014-2015</bpref>
        <bpref>SBAC_PT-MA-Undesignated</bpref>
        <poolproperty property="--ITEMTYPE--" value="EQ" label="EQ" />
        <poolproperty property="Language" value="ENU-Braille" label="Braille English" />
        <itemscoredimension measurementmodel="RAWSCORE" scorepoints="2" weight="1.000000000000000e+000" />
      </testitem>
      <testitem filename="item-187-1448.xml" itemtype="MC">
        <identifier uniqueid="187-1448" version="5644" />
        <bpref>(SBAC_PT)SBAC Math HS-MATH-10-Spring-2014-2015</bpref>
        <bpref>SBAC_PT-MA-Undesignated</bpref>
        <poolproperty property="--ITEMTYPE--" value="MC" label="MC" />
        <poolproperty property="Language" value="ENU-Braille" label="Braille English" />
        <itemscoredimension measurementmodel="RAWSCORE" scorepoints="1" weight="1.000000000000000e+000" />
      </testitem>
      <testitem filename="item-187-1672.xml" itemtype="TI">
        <identifier uniqueid="187-1672" version="4867" />
        <bpref>(SBAC_PT)SBAC Math HS-MATH-10-Spring-2014-2015</bpref>
        <bpref>SBAC_PT-MA-Undesignated</bpref>
        <poolproperty property="--ITEMTYPE--" value="TI" label="TI" />
        <poolproperty property="Language" value="ENU" label="English" />
        <poolproperty property="Language" value="ENU-Braille" label="Braille English" />
        <poolproperty property="Language" value="ESN" label="Spanish" />
        <itemscoredimension measurementmodel="RAWSCORE" scorepoints="1" weight="1.000000000000000e+000" />
      </testitem>
      <testitem filename="item-187-1676.xml" itemtype="GI">
        <identifier uniqueid="187-1676" version="4867" />
        <bpref>(SBAC_PT)SBAC Math HS-MATH-10-Spring-2014-2015</bpref>
        <bpref>SBAC_PT-MA-Undesignated</bpref>
        <poolproperty property="--ITEMTYPE--" value="GI" label="GI" />
        <poolproperty property="Language" value="ENU" label="English" />
        <poolproperty property="Language" value="ESN" label="Spanish" />
        <itemscoredimension measurementmodel="RAWSCORE" scorepoints="1" weight="1.000000000000000e+000" />
      </testitem>
      <testitem filename="item-187-1688.xml" itemtype="MC">
        <identifier uniqueid="187-1688" version="4867" />
        <bpref>(SBAC_PT)SBAC Math HS-MATH-10-Spring-2014-2015</bpref>
        <bpref>SBAC_PT-MA-Undesignated</bpref>
        <poolproperty property="--ITEMTYPE--" value="MC" label="MC" />
        <poolproperty property="Language" value="ENU-Braille" label="Braille English" />
        <itemscoredimension measurementmodel="RAWSCORE" scorepoints="1" weight="1.000000000000000e+000" />
      </testitem>
      <testitem filename="item-187-174.xml" itemtype="ER">
        <identifier uniqueid="187-174" version="4867" />
        <bpref>(SBAC_PT)SBAC Math HS-MATH-10-Spring-2014-2015</bpref>
        <bpref>SBAC_PT-MA-Undesignated</bpref>
        <poolproperty property="--ITEMTYPE--" value="ER" label="ER" />
        <poolproperty property="Language" value="ENU" label="English" />
        <poolproperty property="Language" value="ENU-Braille" label="Braille English" />
        <poolproperty property="Language" value="ESN" label="Spanish" />
        <itemscoredimension measurementmodel="IRTPCL" scorepoints="2" weight="1.000000000000000e+000">
          <itemscoreparameter measurementparameter="b0" value="1.000000000000000e-015" />
          <itemscoreparameter measurementparameter="b1" value="1.000000000000000e-015" />
        </itemscoredimension>
      </testitem>
      <testitem filename="item-187-666.xml" itemtype="MI">
        <identifier uniqueid="187-666" version="4867" />
        <bpref>(SBAC_PT)SBAC Math HS-MATH-10-Spring-2014-2015</bpref>
        <bpref>SBAC_PT-MA-Undesignated</bpref>
        <poolproperty property="--ITEMTYPE--" value="MI" label="MI" />
        <poolproperty property="Language" value="ENU" label="English" />
        <poolproperty property="Language" value="ENU-Braille" label="Braille English" />
        <poolproperty property="Language" value="ESN" label="Spanish" />
        <itemscoredimension measurementmodel="RAWSCORE" scorepoints="1" weight="1.000000000000000e+000" />
      </testitem>
      <testitem filename="item-187-686.xml" itemtype="EQ">
        <identifier uniqueid="187-686" version="4867" />
        <bpref>(SBAC_PT)SBAC Math HS-MATH-10-Spring-2014-2015</bpref>
        <bpref>SBAC_PT-MA-Undesignated</bpref>
        <poolproperty property="--ITEMTYPE--" value="EQ" label="EQ" />
        <poolproperty property="Language" value="ENU" label="English" />
        <poolproperty property="Language" value="ENU-Braille" label="Braille English" />
        <poolproperty property="Language" value="ESN" label="Spanish" />
        <itemscoredimension measurementmodel="RAWSCORE" scorepoints="1" weight="1.000000000000000e+000" />
      </testitem>
      <testitem filename="item-187-766.xml" itemtype="GI">
        <identifier uniqueid="187-766" version="4867" />
        <bpref>(SBAC_PT)SBAC Math HS-MATH-10-Spring-2014-2015</bpref>
        <bpref>SBAC_PT-MA-Undesignated</bpref>
        <poolproperty property="--ITEMTYPE--" value="GI" label="GI" />
        <poolproperty property="Language" value="ENU" label="English" />
        <poolproperty property="Language" value="ESN" label="Spanish" />
        <itemscoredimension measurementmodel="RAWSCORE" scorepoints="1" weight="1.000000000000000e+000" />
      </testitem>
      <testitem filename="item-187-769.xml" itemtype="GI">
        <identifier uniqueid="187-769" version="4867" />
        <bpref>(SBAC_PT)SBAC Math HS-MATH-10-Spring-2014-2015</bpref>
        <bpref>SBAC_PT-MA-Undesignated</bpref>
        <poolproperty property="--ITEMTYPE--" value="GI" label="GI" />
        <poolproperty property="Language" value="ENU" label="English" />
        <poolproperty property="Language" value="ESN" label="Spanish" />
        <itemscoredimension measurementmodel="RAWSCORE" scorepoints="2" weight="1.000000000000000e+000" />
      </testitem>
    </itempool>
    <testform length="8">
      <identifier uniqueid="(SBAC_PT)SBAC Math HS-MATH-10-Spring-2014-2015:Default-ENU" name="(SBAC_PT)SBAC Math HS-MATH-10-Spring-2014-2015:Default-ENU" version="4867" />
      <property name="language" value="ENU" label="English" />
      <poolproperty property="--ITEMTYPE--" value="EQ" label="EQ" itemcount="1" />
      <poolproperty property="--ITEMTYPE--" value="ER" label="ER" itemcount="1" />
      <poolproperty property="--ITEMTYPE--" value="GI" label="GI" itemcount="3" />
      <poolproperty property="--ITEMTYPE--" value="MI" label="MI" itemcount="1" />
      <poolproperty property="--ITEMTYPE--" value="MS" label="MS" itemcount="1" />
      <poolproperty property="--ITEMTYPE--" value="TI" label="TI" itemcount="1" />
      <poolproperty property="Language" value="ENU" label="English" itemcount="8" />
      <poolproperty property="Language" value="ENU-Braille" label="Braille English" itemcount="5" />
      <poolproperty property="Language" value="ESN" label="Spanish" itemcount="8" />
      <formpartition>
        <identifier uniqueid="187-490" name="Math Training HS::SP 14" version="4867" />
        <itemgroup formposition="1" maxitems="ALL" maxresponses="0">
          <identifier uniqueid="187-490:I-187-769" name="187-490:I-187-769" version="4867" />
          <groupitem itemid="187-769" formposition="1" groupposition="1" adminrequired="true" responserequired="true" isactive="true" isfieldtest="true" blockid="A" />
        </itemgroup>
        <itemgroup formposition="2" maxitems="ALL" maxresponses="0">
          <identifier uniqueid="187-490:I-187-174" name="187-490:I-187-174" version="4867" />
          <groupitem itemid="187-174" formposition="2" groupposition="1" adminrequired="true" responserequired="true" isactive="true" isfieldtest="true" blockid="A" />
        </itemgroup>
        <itemgroup formposition="3" maxitems="ALL" maxresponses="0">
          <identifier uniqueid="187-490:I-187-666" name="187-490:I-187-666" version="4867" />
          <groupitem itemid="187-666" formposition="3" groupposition="1" adminrequired="true" responserequired="true" isactive="true" isfieldtest="true" blockid="A" />
        </itemgroup>
        <itemgroup formposition="4" maxitems="ALL" maxresponses="0">
          <identifier uniqueid="187-490:I-187-686" name="187-490:I-187-686" version="4867" />
          <groupitem itemid="187-686" formposition="4" groupposition="1" adminrequired="true" responserequired="true" isactive="true" isfieldtest="true" blockid="A" />
        </itemgroup>
        <itemgroup formposition="5" maxitems="ALL" maxresponses="0">
          <identifier uniqueid="187-490:I-187-1676" name="187-490:I-187-1676" version="4867" />
          <groupitem itemid="187-1676" formposition="5" groupposition="1" adminrequired="true" responserequired="true" isactive="true" isfieldtest="true" blockid="A" />
        </itemgroup>
        <itemgroup formposition="6" maxitems="ALL" maxresponses="0">
          <identifier uniqueid="187-490:I-187-1059" name="187-490:I-187-1059" version="4867" />
          <groupitem itemid="187-1059" formposition="6" groupposition="1" adminrequired="true" responserequired="true" isactive="true" isfieldtest="true" blockid="A" />
        </itemgroup>
        <itemgroup formposition="7" maxitems="ALL" maxresponses="0">
          <identifier uniqueid="187-490:I-187-1672" name="187-490:I-187-1672" version="4867" />
          <groupitem itemid="187-1672" formposition="7" groupposition="1" adminrequired="true" responserequired="true" isactive="true" isfieldtest="true" blockid="A" />
        </itemgroup>
        <itemgroup formposition="8" maxitems="ALL" maxresponses="0">
          <identifier uniqueid="187-490:I-187-766" name="187-490:I-187-766" version="4867" />
          <groupitem itemid="187-766" formposition="8" groupposition="1" adminrequired="true" responserequired="true" isactive="true" isfieldtest="true" blockid="A" />
        </itemgroup>
      </formpartition>
    </testform>
    <testform length="8">
      <identifier uniqueid="(SBAC_PT)SBAC Math HS-MATH-10-Spring-2014-2015:Default-ENU-Braille" name="(SBAC_PT)SBAC Math HS-MATH-10-Spring-2014-2015:Default-ENU-Braille" version="4867" />
      <property name="language" value="ENU-Braille" label="English" />
      <poolproperty property="--ITEMTYPE--" value="EQ" label="EQ" itemcount="2" />
      <poolproperty property="--ITEMTYPE--" value="ER" label="ER" itemcount="1" />
      <poolproperty property="--ITEMTYPE--" value="MC" label="MC" itemcount="2" />
      <poolproperty property="--ITEMTYPE--" value="MI" label="MI" itemcount="1" />
      <poolproperty property="--ITEMTYPE--" value="MS" label="MS" itemcount="1" />
      <poolproperty property="--ITEMTYPE--" value="TI" label="TI" itemcount="1" />
      <poolproperty property="Language" value="ENU" label="English" itemcount="5" />
      <poolproperty property="Language" value="ENU-Braille" label="Braille English" itemcount="8" />
      <poolproperty property="Language" value="ESN" label="Spanish" itemcount="5" />
      <formpartition>
        <identifier uniqueid="187-493" name="Math Training HS::SP 14::Braille" version="4867" />
        <itemgroup formposition="1" maxitems="ALL" maxresponses="0">
          <identifier uniqueid="187-493:I-187-1387" name="187-493:I-187-1387" version="4867" />
          <groupitem itemid="187-1387" formposition="1" groupposition="1" adminrequired="true" responserequired="true" isactive="true" isfieldtest="true" blockid="A" />
        </itemgroup>
        <itemgroup formposition="2" maxitems="ALL" maxresponses="0">
          <identifier uniqueid="187-493:I-187-174" name="187-493:I-187-174" version="4867" />
          <groupitem itemid="187-174" formposition="2" groupposition="1" adminrequired="true" responserequired="true" isactive="true" isfieldtest="true" blockid="A" />
        </itemgroup>
        <itemgroup formposition="3" maxitems="ALL" maxresponses="0">
          <identifier uniqueid="187-493:I-187-666" name="187-493:I-187-666" version="4867" />
          <groupitem itemid="187-666" formposition="3" groupposition="1" adminrequired="true" responserequired="true" isactive="true" isfieldtest="true" blockid="A" />
        </itemgroup>
        <itemgroup formposition="4" maxitems="ALL" maxresponses="0">
          <identifier uniqueid="187-493:I-187-686" name="187-493:I-187-686" version="4867" />
          <groupitem itemid="187-686" formposition="4" groupposition="1" adminrequired="true" responserequired="true" isactive="true" isfieldtest="true" blockid="A" />
        </itemgroup>
        <itemgroup formposition="5" maxitems="ALL" maxresponses="0">
          <identifier uniqueid="187-493:I-187-1688" name="187-493:I-187-1688" version="4867" />
          <groupitem itemid="187-1688" formposition="5" groupposition="1" adminrequired="true" responserequired="true" isactive="true" isfieldtest="true" blockid="A" />
        </itemgroup>
        <itemgroup formposition="6" maxitems="ALL" maxresponses="0">
          <identifier uniqueid="187-493:I-187-1059" name="187-493:I-187-1059" version="4867" />
          <groupitem itemid="187-1059" formposition="6" groupposition="1" adminrequired="true" responserequired="true" isactive="true" isfieldtest="true" blockid="A" />
        </itemgroup>
        <itemgroup formposition="7" maxitems="ALL" maxresponses="0">
          <identifier uniqueid="187-493:I-187-1672" name="187-493:I-187-1672" version="4867" />
          <groupitem itemid="187-1672" formposition="7" groupposition="1" adminrequired="true" responserequired="true" isactive="true" isfieldtest="true" blockid="A" />
        </itemgroup>
        <itemgroup formposition="8" maxitems="ALL" maxresponses="0">
          <identifier uniqueid="187-493:I-187-1448" name="187-493:I-187-1448" version="4867" />
          <groupitem itemid="187-1448" formposition="8" groupposition="1" adminrequired="true" responserequired="true" isactive="true" isfieldtest="true" blockid="A" />
        </itemgroup>
      </formpartition>
    </testform>
    <testform length="8">
      <identifier uniqueid="(SBAC_PT)SBAC Math HS-MATH-10-Spring-2014-2015:Default-ESN" name="(SBAC_PT)SBAC Math HS-MATH-10-Spring-2014-2015:Default-ESN" version="4867" />
      <property name="language" value="ESN" label="Spanish" />
      <poolproperty property="--ITEMTYPE--" value="EQ" label="EQ" itemcount="1" />
      <poolproperty property="--ITEMTYPE--" value="ER" label="ER" itemcount="1" />
      <poolproperty property="--ITEMTYPE--" value="GI" label="GI" itemcount="3" />
      <poolproperty property="--ITEMTYPE--" value="MI" label="MI" itemcount="1" />
      <poolproperty property="--ITEMTYPE--" value="MS" label="MS" itemcount="1" />
      <poolproperty property="--ITEMTYPE--" value="TI" label="TI" itemcount="1" />
      <poolproperty property="Language" value="ENU" label="English" itemcount="8" />
      <poolproperty property="Language" value="ENU-Braille" label="Braille English" itemcount="5" />
      <poolproperty property="Language" value="ESN" label="Spanish" itemcount="8" />
      <formpartition>
        <identifier uniqueid="187-504" name="Math Training HS::SP 14::Spanish" version="4867" />
        <itemgroup formposition="1" maxitems="ALL" maxresponses="0">
          <identifier uniqueid="187-504:I-187-769" name="187-504:I-187-769" version="4867" />
          <groupitem itemid="187-769" formposition="1" groupposition="1" adminrequired="true" responserequired="true" isactive="true" isfieldtest="true" blockid="A" />
        </itemgroup>
        <itemgroup formposition="2" maxitems="ALL" maxresponses="0">
          <identifier uniqueid="187-504:I-187-174" name="187-504:I-187-174" version="4867" />
          <groupitem itemid="187-174" formposition="2" groupposition="1" adminrequired="true" responserequired="true" isactive="true" isfieldtest="true" blockid="A" />
        </itemgroup>
        <itemgroup formposition="3" maxitems="ALL" maxresponses="0">
          <identifier uniqueid="187-504:I-187-666" name="187-504:I-187-666" version="4867" />
          <groupitem itemid="187-666" formposition="3" groupposition="1" adminrequired="true" responserequired="true" isactive="true" isfieldtest="true" blockid="A" />
        </itemgroup>
        <itemgroup formposition="4" maxitems="ALL" maxresponses="0">
          <identifier uniqueid="187-504:I-187-686" name="187-504:I-187-686" version="4867" />
          <groupitem itemid="187-686" formposition="4" groupposition="1" adminrequired="true" responserequired="true" isactive="true" isfieldtest="true" blockid="A" />
        </itemgroup>
        <itemgroup formposition="5" maxitems="ALL" maxresponses="0">
          <identifier uniqueid="187-504:I-187-1676" name="187-504:I-187-1676" version="4867" />
          <groupitem itemid="187-1676" formposition="5" groupposition="1" adminrequired="true" responserequired="true" isactive="true" isfieldtest="true" blockid="A" />
        </itemgroup>
        <itemgroup formposition="6" maxitems="ALL" maxresponses="0">
          <identifier uniqueid="187-504:I-187-1059" name="187-504:I-187-1059" version="4867" />
          <groupitem itemid="187-1059" formposition="6" groupposition="1" adminrequired="true" responserequired="true" isactive="true" isfieldtest="true" blockid="A" />
        </itemgroup>
        <itemgroup formposition="7" maxitems="ALL" maxresponses="0">
          <identifier uniqueid="187-504:I-187-1672" name="187-504:I-187-1672" version="4867" />
          <groupitem itemid="187-1672" formposition="7" groupposition="1" adminrequired="true" responserequired="true" isactive="true" isfieldtest="true" blockid="A" />
        </itemgroup>
        <itemgroup formposition="8" maxitems="ALL" maxresponses="0">
          <identifier uniqueid="187-504:I-187-766" name="187-504:I-187-766" version="4867" />
          <groupitem itemid="187-766" formposition="8" groupposition="1" adminrequired="true" responserequired="true" isactive="true" isfieldtest="true" blockid="A" />
        </itemgroup>
      </formpartition>
    </testform>
    <adminsegment segmentid="(SBAC_PT)SBAC Math HS-MATH-10-Spring-2014-2015" position="1" itemselection="fixedform">
      <segmentblueprint>
        <segmentbpelement bpelementid="SBAC_PT-MA-Undesignated" minopitems="0" maxopitems="8" />
      </segmentblueprint>
      <itemselector type="fixedform">
        <identifier uniqueid="AIR FIXEDFORM1" name="AIR FIXEDFORM" label="AIR FIXEDFORM" version="1.0" />
      </itemselector>
      <segmentform formpartitionid="187-490" />
      <segmentform formpartitionid="187-493" />
      <segmentform formpartitionid="187-504" />
    </adminsegment>
  </administration>
</testspecification>